pytuneteller/__init__.py
pytuneteller/__main__.py
pytuneteller/cli.py
pytuneteller/exceptions.py
pytuneteller/pytuneteller.py
pytuneteller/sites.py
pytuneteller/utils.py
pytuneteller/version.py
pytuneteller/words/adjectives.txt
pytuneteller/words/nouns.txt
pytuneteller-0.2.0.dist-info/AUTHORS.rst
pytuneteller-0.2.0.dist-info/LICENSE
pytuneteller-0.2.0.dist-info/METADATA
pytuneteller-0.2.0.dist-info/WHEEL
pytuneteller-0.2.0.dist-info/entry_points.txt
pytuneteller-0.2.0.dist-info/top_level.txt
pytuneteller-0.2.0.dist-info/RECORD
