Metadata-Version: 2.1
Name: pytuneteller
Version: 0.2.0
Summary: A python horoscope fortune teller made for fun.
Home-page: https://github.com/yujinyuz/pytuneteller
Author: Eugene Oliveros
Author-email: eevoliveros@gmail.com
License: MIT license
Keywords: pytuneteller,horoscope,astrology,fun
Platform: UNKNOWN
Classifier: Development Status :: 2 - Pre-Alpha
Classifier: Intended Audience :: Developers
Classifier: Intended Audience :: End Users/Desktop
Classifier: License :: OSI Approved :: MIT License
Classifier: Natural Language :: English
Classifier: Programming Language :: Python :: 3
Requires-Python: >=3
Requires-Dist: beautifulsoup4
Requires-Dist: docopt
Requires-Dist: requests
